odoo/addons/account_invoice_report_utm_campaign/README.rst
odoo/addons/account_invoice_report_utm_campaign/__init__.py
odoo/addons/account_invoice_report_utm_campaign/__manifest__.py
odoo/addons/account_invoice_report_utm_campaign/i18n/account_invoice_report_utm_campaign.pot
odoo/addons/account_invoice_report_utm_campaign/i18n/it.po
odoo/addons/account_invoice_report_utm_campaign/readme/CONTRIBUTORS.rst
odoo/addons/account_invoice_report_utm_campaign/readme/DESCRIPTION.rst
odoo/addons/account_invoice_report_utm_campaign/report/__init__.py
odoo/addons/account_invoice_report_utm_campaign/report/account_invoice_report.py
odoo/addons/account_invoice_report_utm_campaign/static/description/icon.png
odoo/addons/account_invoice_report_utm_campaign/static/description/index.html
odoo14_addon_account_invoice_report_utm_campaign-14.0.1.0.1.dev5.dist-info/METADATA
odoo14_addon_account_invoice_report_utm_campaign-14.0.1.0.1.dev5.dist-info/WHEEL
odoo14_addon_account_invoice_report_utm_campaign-14.0.1.0.1.dev5.dist-info/top_level.txt
odoo14_addon_account_invoice_report_utm_campaign-14.0.1.0.1.dev5.dist-info/RECORD
