Metadata-Version: 2.1
Name: odoo14-addon-account_invoice_report_utm_campaign
Version: 14.0.1.0.1.dev5
Summary: Add the Campaign, Medium, and Source fields to the Invoice Analysis report.
Home-page: https://github.com/OCA/account-invoice-reporting
Author: Akretion, Odoo Community Association (OCA)
Author-email: support@odoo-community.org
License: AGPL-3
Classifier: Programming Language :: Python
Classifier: Framework :: Odoo
Classifier: Framework :: Odoo :: 14.0
Classifier: License :: OSI Approved :: GNU Affero General Public License v3
Requires-Python: >=3.6
Requires-Dist: odoo<14.1dev,>=14.0a
